[
    {
        "likeability": 8,
        "userEmail": "SJX2iVIpN",
        "userId": 17,
        "userName": "a6J5yE"
    },
    {
        "likeability": -6,
        "userEmail": "TlNYmJBQseNM",
        "userId": -17,
        "userName": "rimC8GlOhOH0b6jv"
    },
    {
        "likeability": -19,
        "userEmail": "KdTPfEg60z",
        "userId": 30,
        "userName": "fL7tTiUi3N"
    },
    {
        "likeability": 30,
        "userEmail": null,
        "userId": 28,
        "userName": "wV"
    },
    {
        "likeability": 13,
        "userEmail": "vNREMlCtrRMdGtFN4nrc",
        "userId": 30,
        "userName": "QQ0QYy2"
    },
    {
        "likeability": 30,
        "userEmail": null,
        "userId": 4,
        "userName": "OFRu7WFau3LvqhWVVlyeTojcIrSk1"
    },
    {
        "likeability": -20,
        "userEmail": "GOcL1wwSP00MEvikrWLQ9L93",
        "userId": 25,
        "userName": ""
    },
    {
        "likeability": 11,
        "userEmail": null,
        "userId": -10,
        "userName": "1QD6g2rRHZRsROPWWBosf6Jft"
    },
    {
        "likeability": 30,
        "userEmail": "7tkRdpVwRPfLOQgQMtkEd",
        "userId": 19,
        "userName": "JJTeyVF75pqVzhFweqJj7znQ8GD8J"
    },
    {
        "likeability": 17,
        "userEmail": "N1qJFMO",
        "userId": -24,
        "userName": "SGoKTHwFrYQnoI"
    }
]